MANIFEST.in
README.md
setup.py
conf/conf.ini
zahlabut/LogTool.py
zahlabut/conf.py
zahlabut.egg-info/PKG-INFO
zahlabut.egg-info/SOURCES.txt
zahlabut.egg-info/dependency_links.txt
zahlabut.egg-info/top_level.txt