Metadata-Version: 2.1
Name: zahlabut
Version: 0.0.2.16
Summary: Extract unique Errors blocks from logs files by given "start time" timestamp
Home-page: https://github.com/zahlabut/LogToolPyPi
Author: Arkady Shtempler
Author-email: arkadysh@gmail.com
License: UNKNOWN
Project-URL: Bug Reports, https://github.com/pypa/sampleproject/issues
Project-URL: GitHub, https://github.com/zahlabut/LogTool
Project-URL: Article, https://opensource.com/article/20/1/logtool-root-cause-identification
Project-URL: Source, https://github.com/zahlabut/LogToolPyPi
Keywords: logs,analyze logs,zahlabut,redhat openstack,extract errors from logs
Platform: UNKNOWN
Classifier: Programming Language :: Python :: 3
Classifier: License :: OSI Approved :: MIT License
Classifier: Operating System :: OS Independent
Requires-Python: >=3.6
